dict2xml/__init__.py
pydict2xml-0.5.0.dist-info/DESCRIPTION.rst
pydict2xml-0.5.0.dist-info/METADATA
pydict2xml-0.5.0.dist-info/metadata.json
pydict2xml-0.5.0.dist-info/RECORD
pydict2xml-0.5.0.dist-info/top_level.txt
pydict2xml-0.5.0.dist-info/WHEEL
