Metadata-Version: 2.0
Name: pydict2xml
Version: 0.5.0
Summary: Small utility to convert a python dict into an xml tree.
Home-page: https://github.com/fernandoflorez/dict2xml
Author: Fernando Flórez
Author-email: fernando@funciton.com
License: UNKNOWN
Platform: UNKNOWN
